platon_utils/__init__.py
platon_utils/__main__.py
platon_utils/abi.py
platon_utils/address.py
platon_utils/applicators.py
platon_utils/bech32.py
platon_utils/conversions.py
platon_utils/crypto.py
platon_utils/currency.py
platon_utils/debug.py
platon_utils/decorators.py
platon_utils/encoding.py
platon_utils/exceptions.py
platon_utils/functional.py
platon_utils/hexadecimal.py
platon_utils/humanize.py
platon_utils/logging.py
platon_utils/module_loading.py
platon_utils/numeric.py
platon_utils/py.typed
platon_utils/toolz.py
platon_utils/types.py
platon_utils/units.py
platon_utils/curried/__init__.py
platon_utils/typing/__init__.py
platon_utils/typing/misc.py
platon_utils-1.2.1.dist-info/LICENSE
platon_utils-1.2.1.dist-info/METADATA
platon_utils-1.2.1.dist-info/WHEEL
platon_utils-1.2.1.dist-info/top_level.txt
platon_utils-1.2.1.dist-info/RECORD
